satispy/__init__.py
satispy/cnf.py
satispy/exception.py
satispy/solution.py
satispy/io/__init__.py
satispy/io/dimacs_cnf.py
satispy/solver/__init__.py
satispy/solver/cadical.py
satispy/solver/cryptominisat.py
satispy/solver/glucose.py
satispy/solver/intel_sat_solver.py
satispy/solver/lingeling.py
satispy/solver/minisat.py
satispy/solver/picosat.py
satispy/solver/sat4j.py
satispy-1.4.dist-info/licenses/LICENSE
satispy-1.4.dist-info/METADATA
satispy-1.4.dist-info/WHEEL
satispy-1.4.dist-info/top_level.txt
satispy-1.4.dist-info/RECORD
